Metadata-Version: 1.0
Name: probdist
Version: 0.1
Summary: Gaussian and Binomial distributions
Home-page: UNKNOWN
Author: Rasyid Sulaeman
Author-email: rasyidrafi@gmail.com
License: UNKNOWN
Platform: UNKNOWN
